foldify/__init__.py
foldify/compat.py
foldify/empty.py
foldify/foldify.py
foldify/settings.py
foldify/tree.py
foldify-0.4.1.data/scripts/__init__.py
foldify-0.4.1.data/scripts/compat.py
foldify-0.4.1.data/scripts/empty.py
foldify-0.4.1.data/scripts/settings.py
foldify-0.4.1.data/scripts/tree.py
foldify-0.4.1.dist-info/DESCRIPTION.rst
foldify-0.4.1.dist-info/METADATA
foldify-0.4.1.dist-info/RECORD
foldify-0.4.1.dist-info/WHEEL
foldify-0.4.1.dist-info/entry_points.txt
foldify-0.4.1.dist-info/metadata.json
foldify-0.4.1.dist-info/top_level.txt
