Metadata-Version: 2.0
Name: foldify
Version: 0.4.1
Summary: Python CLI tools to help manage directory trees and templates
Home-page: https://github.com/gtalarico/foldify
Author: Gui Talarico
Author-email: gui.talarico+pip@gmail.com
License: MIT
Download-URL: https://github.com/gtalarico/foldify/archive/0.3.8.tar.gz
Keywords: folders,directories
Platform: UNKNOWN
Classifier: Development Status :: 3 - Alpha
Classifier: Intended Audience :: Developers
Classifier: License :: OSI Approved :: MIT License
Classifier: Programming Language :: Python :: 2.6
Classifier: Programming Language :: Python :: 2.7
Classifier: Programming Language :: Python :: 3
Classifier: Programming Language :: Python :: 3.3
Classifier: Programming Language :: Python :: 3.4
Classifier: Programming Language :: Python :: 3.5
Requires-Dist: pathlib
